kraken-python/__init__.py
kraken-python/kraken.py
kraken-python/utils.py
kraken_python/__init__.py
kraken_python/kraken.py
kraken_python/utils.py
kraken_python-0.2.dist-info/METADATA
kraken_python-0.2.dist-info/WHEEL
kraken_python-0.2.dist-info/top_level.txt
kraken_python-0.2.dist-info/RECORD
