Metadata-Version: 2.4
Name: kraken-python
Version: 0.2
Summary: Secure anonymous Telegram bot library
Home-page: https://github.com/NEFORCEO
Author: Anonymous Developer
Classifier: Programming Language :: Python :: 3
Classifier: License :: OSI Approved :: MIT License
Classifier: Operating System :: OS Independent
Requires-Dist: pyTelegramBotAPI
Dynamic: author
Dynamic: classifier
Dynamic: description-content-type
Dynamic: home-page
Dynamic: requires-dist
Dynamic: summary
